pykvdb/__init__.py
pykvdb-0.1.3.dist-info/LICENSE
pykvdb-0.1.3.dist-info/METADATA
pykvdb-0.1.3.dist-info/WHEEL
pykvdb-0.1.3.dist-info/top_level.txt
pykvdb-0.1.3.dist-info/RECORD
