Metadata-Version: 2.1
Name: pykvdb
Version: 0.1.3
Summary: A simple key-value database in python.
Home-page: https://github.com/bingal/pykvdb
Author: Bingal
Author-email: bingalsky@gmail.com
License: MIT
Platform: UNKNOWN
Classifier: License :: OSI Approved :: MIT License
Classifier: Programming Language :: Python
Classifier: Programming Language :: Python :: 3
Classifier: Programming Language :: Python :: 3.6
Classifier: Programming Language :: Python :: Implementation :: CPython
Classifier: Programming Language :: Python :: Implementation :: PyPy
Requires-Python: >=3.6.0
License-File: LICENSE
Requires-Dist: lmdb
